puc8/__init__.py
puc8/asm.py
puc8/assembler.py
puc8/cc.py
puc8/compiler.py
puc8/disassembler.py
puc8/emitter.py
puc8/instructions.py
puc8/simulator.py
puc8/ppci/__init__.py
puc8/ppci/api.py
puc8/ppci/cil.py
puc8/ppci/common.py
puc8/ppci/ir.py
puc8/ppci/runtime.py
puc8/ppci/arch/__init__.py
puc8/ppci/arch/arch.py
puc8/ppci/arch/arch_info.py
puc8/ppci/arch/asm_printer.py
puc8/ppci/arch/cc.py
puc8/ppci/arch/data_instructions.py
puc8/ppci/arch/effects.py
puc8/ppci/arch/encoding.py
puc8/ppci/arch/example.py
puc8/ppci/arch/generic_instructions.py
puc8/ppci/arch/isa.py
puc8/ppci/arch/registers.py
puc8/ppci/arch/runtime.py
puc8/ppci/arch/stack.py
puc8/ppci/arch/target_list.py
puc8/ppci/arch/token.py
puc8/ppci/arch/puc8/__init__.py
puc8/ppci/arch/puc8/arch.py
puc8/ppci/arch/puc8/instructions.py
puc8/ppci/arch/puc8/registers.py
puc8/ppci/binutils/__init__.py
puc8/ppci/binutils/archive.py
puc8/ppci/binutils/assembler.py
puc8/ppci/binutils/debuginfo.py
puc8/ppci/binutils/disasm.py
puc8/ppci/binutils/layout.py
puc8/ppci/binutils/linker.py
puc8/ppci/binutils/objectfile.py
puc8/ppci/binutils/outstream.py
puc8/ppci/binutils/dbg/__init__.py
puc8/ppci/binutils/dbg/cli.py
puc8/ppci/binutils/dbg/debug_driver.py
puc8/ppci/binutils/dbg/debugger.py
puc8/ppci/binutils/dbg/dummy_driver.py
puc8/ppci/binutils/dbg/event.py
puc8/ppci/binutils/dbg/linux64debugdriver.py
puc8/ppci/binutils/dbg/ptcli.py
puc8/ppci/binutils/dbg/gdb/__init__.py
puc8/ppci/binutils/dbg/gdb/client.py
puc8/ppci/binutils/dbg/gdb/rsp.py
puc8/ppci/binutils/dbg/gdb/transport.py
puc8/ppci/cil/__init__.py
puc8/ppci/cil/io.py
puc8/ppci/codegen/__init__.py
puc8/ppci/codegen/burg.grammar
puc8/ppci/codegen/burg.py
puc8/ppci/codegen/codegen.py
puc8/ppci/codegen/dagsplit.py
puc8/ppci/codegen/flowgraph.py
puc8/ppci/codegen/instructionscheduler.py
puc8/ppci/codegen/instructionselector.py
puc8/ppci/codegen/interferencegraph.py
puc8/ppci/codegen/irdag.py
puc8/ppci/codegen/peephole.py
puc8/ppci/codegen/registerallocator.py
puc8-0.1.4.dist-info/LICENSE
puc8-0.1.4.dist-info/METADATA
puc8-0.1.4.dist-info/WHEEL
puc8-0.1.4.dist-info/entry_points.txt
puc8-0.1.4.dist-info/top_level.txt
puc8-0.1.4.dist-info/RECORD
